fromjson.py
fromjson-0.1.0.dist-info/LICENSE
fromjson-0.1.0.dist-info/WHEEL
fromjson-0.1.0.dist-info/METADATA
fromjson-0.1.0.dist-info/RECORD
