Metadata-Version: 2.1
Name: fromjson
Version: 0.1.0
Summary: Easily read objects from json
Home-page: https://git.sr.ht/~ilikeavocadoes/fromjson
License: Zlib
Author: Lassi Haasio
Requires-Python: >=3.8,<4.0
Classifier: License :: OSI Approved
Classifier: Programming Language :: Python :: 3
Classifier: Programming Language :: Python :: 3.8
Classifier: Programming Language :: Python :: 3.9
Project-URL: Repository, https://git.sr.ht/~ilikeavocadoes/fromjson
